vosk_model_ko/__init__.py
vosk_model_ko/model/README
vosk_model_ko/model/am/final.mdl
vosk_model_ko/model/conf/mfcc.conf
vosk_model_ko/model/conf/model.conf
vosk_model_ko/model/graph/Gr.fst
vosk_model_ko/model/graph/HCLr.fst
vosk_model_ko/model/graph/disambig_tid.int
vosk_model_ko/model/graph/phones.txt
vosk_model_ko/model/graph/phones/word_boundary.int
vosk_model_ko/model/ivector/final.dubm
vosk_model_ko/model/ivector/final.ie
vosk_model_ko/model/ivector/final.mat
vosk_model_ko/model/ivector/global_cmvn.stats
vosk_model_ko/model/ivector/online_cmvn.conf
vosk_model_ko/model/ivector/splice.conf
vosk_model_ko-0.1.0.dist-info/METADATA
vosk_model_ko-0.1.0.dist-info/WHEEL
vosk_model_ko-0.1.0.dist-info/top_level.txt
vosk_model_ko-0.1.0.dist-info/RECORD
