Metadata-Version: 2.1
Name: vosk-model-ko
Version: 0.1.0
Summary: Pre-packaged Vosk Korean model
Author: Generated by ChatGPT
